[{"id": 103694377, "node_id": "MDEwOlJlcG9zaXRvcnkxMDM2OTQzNzc=", "name": "open-liberty", "full_name": "OpenLiberty/open-liberty", "private": false, "owner": {"login": "OpenLiberty", "id": 28316667, "node_id": "MDEyOk9yZ2FuaXphdGlvbjI4MzE2NjY3", "avatar_url": "https://avatars.githubusercontent.com/u/28316667?v=4", "gravatar_id": "", "url": "https://api.github.com/users/OpenLiberty", "html_url": "https://github.com/OpenLiberty", "followers_url": "https://api.github.com/users/OpenLiberty/followers", "following_url": "https://api.github.com/users/OpenLiberty/following{/other_user}", "gists_url": "https://api.github.com/users/OpenLiberty/gists{/gist_id}", "starred_url": "https://api.github.com/users/OpenLiberty/starred{/owner}{/repo}", "subscriptions_url": "https://api.github.com/users/OpenLiberty/subscriptions", "organizations_url": "https://api.github.com/users/OpenLiberty/orgs", "repos_url": "https://api.github.com/users/OpenLiberty/repos", "events_url": "https://api.github.com/users/OpenLiberty/events{/privacy}", "received_events_url": "https://api.github.com/users/OpenLiberty/received_events", "type": "Organization", "site_admin": false}, "html_url": "https://github.com/OpenLiberty/open-liberty", "description": "Open Liberty is a highly composable, fast to start, dynamic application server runtime environment ", "fork": false, "url": "https://api.github.com/repos/OpenLiberty/open-liberty", "forks_url": "https://api.github.com/repos/OpenLiberty/open-liberty/forks", "keys_url": "https://api.github.com/repos/OpenLiberty/open-liberty/keys{/key_id}", "collaborators_url": "https://api.github.com/repos/OpenLiberty/open-liberty/collaborators{/collaborator}", "teams_url": "https://api.github.com/repos/OpenLiberty/open-liberty/teams", "hooks_url": "https://api.github.com/repos/OpenLiberty/open-liberty/hooks", "issue_events_url": "https://api.github.com/repos/OpenLiberty/open-liberty/issues/events{/number}", "events_url": "https://api.github.com/repos/OpenLiberty/open-liberty/events", "assignees_url": "https://api.github.com/repos/OpenLiberty/open-liberty/assignees{/user}", "branches_url": "https://api.github.com/repos/OpenLiberty/open-liberty/branches{/branch}", "tags_url": "https://api.github.com/repos/OpenLiberty/open-liberty/tags", "blobs_url": "https://api.github.com/repos/OpenLiberty/open-liberty/git/blobs{/sha}", "git_tags_url": "https://api.github.com/repos/OpenLiberty/open-liberty/git/tags{/sha}", "git_refs_url": "https://api.github.com/repos/OpenLiberty/open-liberty/git/refs{/sha}", "trees_url": "https://api.github.com/repos/OpenLiberty/open-liberty/git/trees{/sha}", "statuses_url": "https://api.github.com/repos/OpenLiberty/open-liberty/statuses/{sha}", "languages_url": "https://api.github.com/repos/OpenLiberty/open-liberty/languages", "stargazers_url": "https://api.github.com/repos/OpenLiberty/open-liberty/stargazers", "contributors_url": "https://api.github.com/repos/OpenLiberty/open-liberty/contributors", "subscribers_url": "https://api.github.com/repos/OpenLiberty/open-liberty/subscribers", "subscription_url": "https://api.github.com/repos/OpenLiberty/open-liberty/subscription", "commits_url": "https://api.github.com/repos/OpenLiberty/open-liberty/commits{/sha}", "git_commits_url": "https://api.github.com/repos/OpenLiberty/open-liberty/git/commits{/sha}", "comments_url": "https://api.github.com/repos/OpenLiberty/open-liberty/comments{/number}", "issue_comment_url": "https://api.github.com/repos/OpenLiberty/open-liberty/issues/comments{/number}", "contents_url": "https://api.github.com/repos/OpenLiberty/open-liberty/contents/{+path}", "compare_url": "https://api.github.com/repos/OpenLiberty/open-liberty/compare/{base}...{head}", "merges_url": "https://api.github.com/repos/OpenLiberty/open-liberty/merges", "archive_url": "https://api.github.com/repos/OpenLiberty/open-liberty/{archive_format}{/ref}", "downloads_url": "https://api.github.com/repos/OpenLiberty/open-liberty/downloads", "issues_url": "https://api.github.com/repos/OpenLiberty/open-liberty/issues{/number}", "pulls_url": "https://api.github.com/repos/OpenLiberty/open-liberty/pulls{/number}", "milestones_url": "https://api.github.com/repos/OpenLiberty/open-liberty/milestones{/number}", "notifications_url": "https://api.github.com/repos/OpenLiberty/open-liberty/notifications{?since,all,participating}", "labels_url": "https://api.github.com/repos/OpenLiberty/open-liberty/labels{/name}", "releases_url": "https://api.github.com/repos/OpenLiberty/open-liberty/releases{/id}", "deployments_url": "https://api.github.com/repos/OpenLiberty/open-liberty/deployments", "created_at": "2017-09-15T19:34:25Z", "updated_at": "2022-10-23T08:24:20Z", "pushed_at": "2022-10-25T21:02:57Z", "git_url": "git://github.com/OpenLiberty/open-liberty.git", "ssh_url": "git@github.com:OpenLiberty/open-liberty.git", "clone_url": "https://github.com/OpenLiberty/open-liberty.git", "svn_url": "https://github.com/OpenLiberty/open-liberty", "homepage": "https://openliberty.io", "size": 851157, "stargazers_count": 1018, "watchers_count": 1018, "language": "Java", "has_issues": true, "has_projects": true, "has_downloads": true, "has_wiki": true, "has_pages": false, "forks_count": 519, "mirror_url": null, "archived": false, "disabled": false, "open_issues_count": 2304, "license": {"key": "epl-1.0", "name": "Eclipse Public License 1.0", "spdx_id": "EPL-1.0", "url": "https://api.github.com/licenses/epl-1.0", "node_id": "MDc6TGljZW5zZTc="}, "allow_forking": true, "is_template": false, "web_commit_signoff_required": false, "topics": ["hacktoberfest"], "visibility": "public", "forks": 519, "open_issues": 2304, "watchers": 1018, "default_branch": "integration", "permissions": {"admin": false, "maintain": false, "push": false, "triage": false, "pull": true}}, {"id": 118770621, "node_id": "MDEwOlJlcG9zaXRvcnkxMTg3NzA2MjE=", "name": "JavaExamples", "full_name": "bpaskin/JavaExamples", "private": false, "owner": {"login": "bpaskin", "id": 21156194, "node_id": "MDQ6VXNlcjIxMTU2MTk0", "avatar_url": "https://avatars.githubusercontent.com/u/21156194?v=4", "gravatar_id": "", "url": "https://api.github.com/users/bpaskin", "html_url": "https://github.com/bpaskin", "followers_url": "https://api.github.com/users/bpaskin/followers", "following_url": "https://api.github.com/users/bpaskin/following{/other_user}", "gists_url": "https://api.github.com/users/bpaskin/gists{/gist_id}", "starred_url": "https://api.github.com/users/bpaskin/starred{/owner}{/repo}", "subscriptions_url": "https://api.github.com/users/bpaskin/subscriptions", "organizations_url": "https://api.github.com/users/bpaskin/orgs", "repos_url": "https://api.github.com/users/bpaskin/repos", "events_url": "https://api.github.com/users/bpaskin/events{/privacy}", "received_events_url": "https://api.github.com/users/bpaskin/received_events", "type": "User", "site_admin": false}, "html_url": "https://github.com/bpaskin/JavaExamples", "description": null, "fork": false, "url": "https://api.github.com/repos/bpaskin/JavaExamples", "forks_url": "https://api.github.com/repos/bpaskin/JavaExamples/forks", "keys_url": "https://api.github.com/repos/bpaskin/JavaExamples/keys{/key_id}", "collaborators_url": "https://api.github.com/repos/bpaskin/JavaExamples/collaborators{/collaborator}", "teams_url": "https://api.github.com/repos/bpaskin/JavaExamples/teams", "hooks_url": "https://api.github.com/repos/bpaskin/JavaExamples/hooks", "issue_events_url": "https://api.github.com/repos/bpaskin/JavaExamples/issues/events{/number}", "events_url": "https://api.github.com/repos/bpaskin/JavaExamples/events", "assignees_url": "https://api.github.com/repos/bpaskin/JavaExamples/assignees{/user}", "branches_url": "https://api.github.com/repos/bpaskin/JavaExamples/branches{/branch}", "tags_url": "https://api.github.com/repos/bpaskin/JavaExamples/tags", "blobs_url": "https://api.github.com/repos/bpaskin/JavaExamples/git/blobs{/sha}", "git_tags_url": "https://api.github.com/repos/bpaskin/JavaExamples/git/tags{/sha}", "git_refs_url": "https://api.github.com/repos/bpaskin/JavaExamples/git/refs{/sha}", "trees_url": "https://api.github.com/repos/bpaskin/JavaExamples/git/trees{/sha}", "statuses_url": "https://api.github.com/repos/bpaskin/JavaExamples/statuses/{sha}", "languages_url": "https://api.github.com/repos/bpaskin/JavaExamples/languages", "stargazers_url": "https://api.github.com/repos/bpaskin/JavaExamples/stargazers", "contributors_url": "https://api.github.com/repos/bpaskin/JavaExamples/contributors", "subscribers_url": "https://api.github.com/repos/bpaskin/JavaExamples/subscribers", "subscription_url": "https://api.github.com/repos/bpaskin/JavaExamples/subscription", "commits_url": "https://api.github.com/repos/bpaskin/JavaExamples/commits{/sha}", "git_commits_url": "https://api.github.com/repos/bpaskin/JavaExamples/git/commits{/sha}", "comments_url": "https://api.github.com/repos/bpaskin/JavaExamples/comments{/number}", "issue_comment_url": "https://api.github.com/repos/bpaskin/JavaExamples/issues/comments{/number}", "contents_url": "https://api.github.com/repos/bpaskin/JavaExamples/contents/{+path}", "compare_url": "https://api.github.com/repos/bpaskin/JavaExamples/compare/{base}...{head}", "merges_url": "https://api.github.com/repos/bpaskin/JavaExamples/merges", "archive_url": "https://api.github.com/repos/bpaskin/JavaExamples/{archive_format}{/ref}", "downloads_url": "https://api.github.com/repos/bpaskin/JavaExamples/downloads", "issues_url": "https://api.github.com/repos/bpaskin/JavaExamples/issues{/number}", "pulls_url": "https://api.github.com/repos/bpaskin/JavaExamples/pulls{/number}", "milestones_url": "https://api.github.com/repos/bpaskin/JavaExamples/milestones{/number}", "notifications_url": "https://api.github.com/repos/bpaskin/JavaExamples/notifications{?since,all,participating}", "labels_url": "https://api.github.com/repos/bpaskin/JavaExamples/labels{/name}", "releases_url": "https://api.github.com/repos/bpaskin/JavaExamples/releases{/id}", "deployments_url": "https://api.github.com/repos/bpaskin/JavaExamples/deployments", "created_at": "2018-01-24T13:41:47Z", "updated_at": "2022-03-02T14:50:48Z", "pushed_at": "2022-06-28T22:56:38Z", "git_url": "git://github.com/bpaskin/JavaExamples.git", "ssh_url": "git@github.com:bpaskin/JavaExamples.git", "clone_url": "https://github.com/bpaskin/JavaExamples.git", "svn_url": "https://github.com/bpaskin/JavaExamples", "homepage": null, "size": 453, "stargazers_count": 10, "watchers_count": 10, "language": "Java", "has_issues": true, "has_projects": true, "has_downloads": true, "has_wiki": true, "has_pages": false, "forks_count": 8, "mirror_url": null, "archived": false, "disabled": false, "open_issues_count": 0, "license": null, "allow_forking": true, "is_template": false, "web_commit_signoff_required": false, "topics": [], "visibility": "public", "forks": 8, "open_issues": 0, "watchers": 10, "default_branch": "master", "permissions": {"admin": false, "maintain": false, "push": false, "triage": false, "pull": true}}, {"id": 100059061, "node_id": "MDEwOlJlcG9zaXRvcnkxMDAwNTkwNjE=", "name": "openliberty.io", "full_name": "OpenLiberty/openliberty.io", "private": false, "owner": {"login": "OpenLiberty", "id": 28316667, "node_id": "MDEyOk9yZ2FuaXphdGlvbjI4MzE2NjY3", "avatar_url": "https://avatars.githubusercontent.com/u/28316667?v=4", "gravatar_id": "", "url": "https://api.github.com/users/OpenLiberty", "html_url": "https://github.com/OpenLiberty", "followers_url": "https://api.github.com/users/OpenLiberty/followers", "following_url": "https://api.github.com/users/OpenLiberty/following{/other_user}", "gists_url": "https://api.github.com/users/OpenLiberty/gists{/gist_id}", "starred_url": "https://api.github.com/users/OpenLiberty/starred{/owner}{/repo}", "subscriptions_url": "https://api.github.com/users/OpenLiberty/subscriptions", "organizations_url": "https://api.github.com/users/OpenLiberty/orgs", "repos_url": "https://api.github.com/users/OpenLiberty/repos", "events_url": "https://api.github.com/users/OpenLiberty/events{/privacy}", "received_events_url": "https://api.github.com/users/OpenLiberty/received_events", "type": "Organization", "site_admin": false}, "html_url": "https://github.com/OpenLiberty/openliberty.io", "description": "Open Liberty website", "fork": false, "url": "https://api.github.com/repos/OpenLiberty/openliberty.io", "forks_url": "https://api.github.com/repos/OpenLiberty/openliberty.io/forks", "keys_url": "https://api.github.com/repos/OpenLiberty/openliberty.io/keys{/key_id}", "collaborators_url": "https://api.github.com/repos/OpenLiberty/openliberty.io/collaborators{/collaborator}", "teams_url": "https://api.github.com/repos/OpenLiberty/openliberty.io/teams", "hooks_url": "https://api.github.com/repos/OpenLiberty/openliberty.io/hooks", "issue_events_url": "https://api.github.com/repos/OpenLiberty/openliberty.io/issues/events{/number}", "events_url": "https://api.github.com/repos/OpenLiberty/openliberty.io/events", "assignees_url": "https://api.github.com/repos/OpenLiberty/openliberty.io/assignees{/user}", "branches_url": "https://api.github.com/repos/OpenLiberty/openliberty.io/branches{/branch}", "tags_url": "https://api.github.com/repos/OpenLiberty/openliberty.io/tags", "blobs_url": "https://api.github.com/repos/OpenLiberty/openliberty.io/git/blobs{/sha}", "git_tags_url": "https://api.github.com/repos/OpenLiberty/openliberty.io/git/tags{/sha}", "git_refs_url": "https://api.github.com/repos/OpenLiberty/openliberty.io/git/refs{/sha}", "trees_url": "https://api.github.com/repos/OpenLiberty/openliberty.io/git/trees{/sha}", "statuses_url": "https://api.github.com/repos/OpenLiberty/openliberty.io/statuses/{sha}", "languages_url": "https://api.github.com/repos/OpenLiberty/openliberty.io/languages", "stargazers_url": "https://api.github.com/repos/OpenLiberty/openliberty.io/stargazers", "contributors_url": "https://api.github.com/repos/OpenLiberty/openliberty.io/contributors", "subscribers_url": "https://api.github.com/repos/OpenLiberty/openliberty.io/subscribers", "subscription_url": "https://api.github.com/repos/OpenLiberty/openliberty.io/subscription", "commits_url": "https://api.github.com/repos/OpenLiberty/openliberty.io/commits{/sha}", "git_commits_url": "https://api.github.com/repos/OpenLiberty/openliberty.io/git/commits{/sha}", "comments_url": "https://api.github.com/repos/OpenLiberty/openliberty.io/comments{/number}", "issue_comment_url": "https://api.github.com/repos/OpenLiberty/openliberty.io/issues/comments{/number}", "contents_url": "https://api.github.com/repos/OpenLiberty/openliberty.io/contents/{+path}", "compare_url": "https://api.github.com/repos/OpenLiberty/openliberty.io/compare/{base}...{head}", "merges_url": "https://api.github.com/repos/OpenLiberty/openliberty.io/merges", "archive_url": "https://api.github.com/repos/OpenLiberty/openliberty.io/{archive_format}{/ref}", "downloads_url": "https://api.github.com/repos/OpenLiberty/openliberty.io/downloads", "issues_url": "https://api.github.com/repos/OpenLiberty/openliberty.io/issues{/number}", "pulls_url": "https://api.github.com/repos/OpenLiberty/openliberty.io/pulls{/number}", "milestones_url": "https://api.github.com/repos/OpenLiberty/openliberty.io/milestones{/number}", "notifications_url": "https://api.github.com/repos/OpenLiberty/openliberty.io/notifications{?since,all,participating}", "labels_url": "https://api.github.com/repos/OpenLiberty/openliberty.io/labels{/name}", "releases_url": "https://api.github.com/repos/OpenLiberty/openliberty.io/releases{/id}", "deployments_url": "https://api.github.com/repos/OpenLiberty/openliberty.io/deployments", "created_at": "2017-08-11T18:12:56Z", "updated_at": "2022-09-29T21:16:15Z", "pushed_at": "2022-10-25T17:30:40Z", "git_url": "git://github.com/OpenLiberty/openliberty.io.git", "ssh_url": "git@github.com:OpenLiberty/openliberty.io.git", "clone_url": "https://github.com/OpenLiberty/openliberty.io.git", "svn_url": "https://github.com/OpenLiberty/openliberty.io", "homepage": "https://openliberty.io", "size": 62444, "stargazers_count": 43, "watchers_count": 43, "language": "JavaScript", "has_issues": true, "has_projects": true, "has_downloads": true, "has_wiki": true, "has_pages": false, "forks_count": 37, "mirror_url": null, "archived": false, "disabled": false, "open_issues_count": 112, "license": {"key": "other", "name": "Other", "spdx_id": "NOASSERTION", "url": null, "node_id": "MDc6TGljZW5zZTA="}, "allow_forking": true, "is_template": false, "web_commit_signoff_required": false, "topics": [], "visibility": "public", "forks": 37, "open_issues": 112, "watchers": 43, "default_branch": "prod", "permissions": {"admin": false, "maintain": false, "push": false, "triage": false, "pull": true}}, {"id": 219860459, "node_id": "MDEwOlJlcG9zaXRvcnkyMTk4NjA0NTk=", "name": "was-kerberos-database", "full_name": "mswatosh/was-kerberos-database", "private": false, "owner": {"login": "mswatosh", "id": 21284019, "node_id": "MDQ6VXNlcjIxMjg0MDE5", "avatar_url": "https://avatars.githubusercontent.com/u/21284019?v=4", "gravatar_id": "", "url": "https://api.github.com/users/mswatosh", "html_url": "https://github.com/mswatosh", "followers_url": "https://api.github.com/users/mswatosh/followers", "following_url": "https://api.github.com/users/mswatosh/following{/other_user}", "gists_url": "https://api.github.com/users/mswatosh/gists{/gist_id}", "starred_url": "https://api.github.com/users/mswatosh/starred{/owner}{/repo}", "subscriptions_url": "https://api.github.com/users/mswatosh/subscriptions", "organizations_url": "https://api.github.com/users/mswatosh/orgs", "repos_url": "https://api.github.com/users/mswatosh/repos", "events_url": "https://api.github.com/users/mswatosh/events{/privacy}", "received_events_url": "https://api.github.com/users/mswatosh/received_events", "type": "User", "site_admin": false}, "html_url": "https://github.com/mswatosh/was-kerberos-database", "description": null, "fork": false, "url": "https://api.github.com/repos/mswatosh/was-kerberos-database", "forks_url": "https://api.github.com/repos/mswatosh/was-kerberos-database/forks", "keys_url": "https://api.github.com/repos/mswatosh/was-kerberos-database/keys{/key_id}", "collaborators_url": "https://api.github.com/repos/mswatosh/was-kerberos-database/collaborators{/collaborator}", "teams_url": "https://api.github.com/repos/mswatosh/was-kerberos-database/teams", "hooks_url": "https://api.github.com/repos/mswatosh/was-kerberos-database/hooks", "issue_events_url": "https://api.github.com/repos/mswatosh/was-kerberos-database/issues/events{/number}", "events_url": "https://api.github.com/repos/mswatosh/was-kerberos-database/events", "assignees_url": "https://api.github.com/repos/mswatosh/was-kerberos-database/assignees{/user}", "branches_url": "https://api.github.com/repos/mswatosh/was-kerberos-database/branches{/branch}", "tags_url": "https://api.github.com/repos/mswatosh/was-kerberos-database/tags", "blobs_url": "https://api.github.com/repos/mswatosh/was-kerberos-database/git/blobs{/sha}", "git_tags_url": "https://api.github.com/repos/mswatosh/was-kerberos-database/git/tags{/sha}", "git_refs_url": "https://api.github.com/repos/mswatosh/was-kerberos-database/git/refs{/sha}", "trees_url": "https://api.github.com/repos/mswatosh/was-kerberos-database/git/trees{/sha}", "statuses_url": "https://api.github.com/repos/mswatosh/was-kerberos-database/statuses/{sha}", "languages_url": "https://api.github.com/repos/mswatosh/was-kerberos-database/languages", "stargazers_url": "https://api.github.com/repos/mswatosh/was-kerberos-database/stargazers", "contributors_url": "https://api.github.com/repos/mswatosh/was-kerberos-database/contributors", "subscribers_url": "https://api.github.com/repos/mswatosh/was-kerberos-database/subscribers", "subscription_url": "https://api.github.com/repos/mswatosh/was-kerberos-database/subscription", "commits_url": "https://api.github.com/repos/mswatosh/was-kerberos-database/commits{/sha}", "git_commits_url": "https://api.github.com/repos/mswatosh/was-kerberos-database/git/commits{/sha}", "comments_url": "https://api.github.com/repos/mswatosh/was-kerberos-database/comments{/number}", "issue_comment_url": "https://api.github.com/repos/mswatosh/was-kerberos-database/issues/comments{/number}", "contents_url": "https://api.github.com/repos/mswatosh/was-kerberos-database/contents/{+path}", "compare_url": "https://api.github.com/repos/mswatosh/was-kerberos-database/compare/{base}...{head}", "merges_url": "https://api.github.com/repos/mswatosh/was-kerberos-database/merges", "archive_url": "https://api.github.com/repos/mswatosh/was-kerberos-database/{archive_format}{/ref}", "downloads_url": "https://api.github.com/repos/mswatosh/was-kerberos-database/downloads", "issues_url": "https://api.github.com/repos/mswatosh/was-kerberos-database/issues{/number}", "pulls_url": "https://api.github.com/repos/mswatosh/was-kerberos-database/pulls{/number}", "milestones_url": "https://api.github.com/repos/mswatosh/was-kerberos-database/milestones{/number}", "notifications_url": "https://api.github.com/repos/mswatosh/was-kerberos-database/notifications{?since,all,participating}", "labels_url": "https://api.github.com/repos/mswatosh/was-kerberos-database/labels{/name}", "releases_url": "https://api.github.com/repos/mswatosh/was-kerberos-database/releases{/id}", "deployments_url": "https://api.github.com/repos/mswatosh/was-kerberos-database/deployments", "created_at": "2019-11-05T22:13:21Z", "updated_at": "2021-06-10T15:37:48Z", "pushed_at": "2021-06-10T15:37:42Z", "git_url": "git://github.com/mswatosh/was-kerberos-database.git", "ssh_url": "git@github.com:mswatosh/was-kerberos-database.git", "clone_url": "https://github.com/mswatosh/was-kerberos-database.git", "svn_url": "https://github.com/mswatosh/was-kerberos-database", "homepage": null, "size": 151, "stargazers_count": 3, "watchers_count": 3, "language": "Python", "has_issues": true, "has_projects": true, "has_downloads": true, "has_wiki": true, "has_pages": false, "forks_count": 2, "mirror_url": null, "archived": false, "disabled": false, "open_issues_count": 0, "license": null, "allow_forking": true, "is_template": false, "web_commit_signoff_required": false, "topics": ["database-access", "kerberos", "websphere"], "visibility": "public", "forks": 2, "open_issues": 0, "watchers": 3, "default_branch": "master", "permissions": {"admin": false, "maintain": false, "push": false, "triage": false, "pull": true}}, {"id": 175253587, "node_id": "MDEwOlJlcG9zaXRvcnkxNzUyNTM1ODc=", "name": "dockerdebug", "full_name": "kgibm/dockerdebug", "private": false, "owner": {"login": "kgibm", "id": 6618433, "node_id": "MDQ6VXNlcjY2MTg0MzM=", "avatar_url": "https://avatars.githubusercontent.com/u/6618433?v=4", "gravatar_id": "", "url": "https://api.github.com/users/kgibm", "html_url": "https://github.com/kgibm", "followers_url": "https://api.github.com/users/kgibm/followers", "following_url": "https://api.github.com/users/kgibm/following{/other_user}", "gists_url": "https://api.github.com/users/kgibm/gists{/gist_id}", "starred_url": "https://api.github.com/users/kgibm/starred{/owner}{/repo}", "subscriptions_url": "https://api.github.com/users/kgibm/subscriptions", "organizations_url": "https://api.github.com/users/kgibm/orgs", "repos_url": "https://api.github.com/users/kgibm/repos", "events_url": "https://api.github.com/users/kgibm/events{/privacy}", "received_events_url": "https://api.github.com/users/kgibm/received_events", "type": "User", "site_admin": false}, "html_url": "https://github.com/kgibm/dockerdebug", "description": null, "fork": false, "url": "https://api.github.com/repos/kgibm/dockerdebug", "forks_url": "https://api.github.com/repos/kgibm/dockerdebug/forks", "keys_url": "https://api.github.com/repos/kgibm/dockerdebug/keys{/key_id}", "collaborators_url": "https://api.github.com/repos/kgibm/dockerdebug/collaborators{/collaborator}", "teams_url": "https://api.github.com/repos/kgibm/dockerdebug/teams", "hooks_url": "https://api.github.com/repos/kgibm/dockerdebug/hooks", "issue_events_url": "https://api.github.com/repos/kgibm/dockerdebug/issues/events{/number}", "events_url": "https://api.github.com/repos/kgibm/dockerdebug/events", "assignees_url": "https://api.github.com/repos/kgibm/dockerdebug/assignees{/user}", "branches_url": "https://api.github.com/repos/kgibm/dockerdebug/branches{/branch}", "tags_url": "https://api.github.com/repos/kgibm/dockerdebug/tags", "blobs_url": "https://api.github.com/repos/kgibm/dockerdebug/git/blobs{/sha}", "git_tags_url": "https://api.github.com/repos/kgibm/dockerdebug/git/tags{/sha}", "git_refs_url": "https://api.github.com/repos/kgibm/dockerdebug/git/refs{/sha}", "trees_url": "https://api.github.com/repos/kgibm/dockerdebug/git/trees{/sha}", "statuses_url": "https://api.github.com/repos/kgibm/dockerdebug/statuses/{sha}", "languages_url": "https://api.github.com/repos/kgibm/dockerdebug/languages", "stargazers_url": "https://api.github.com/repos/kgibm/dockerdebug/stargazers", "contributors_url": "https://api.github.com/repos/kgibm/dockerdebug/contributors", "subscribers_url": "https://api.github.com/repos/kgibm/dockerdebug/subscribers", "subscription_url": "https://api.github.com/repos/kgibm/dockerdebug/subscription", "commits_url": "https://api.github.com/repos/kgibm/dockerdebug/commits{/sha}", "git_commits_url": "https://api.github.com/repos/kgibm/dockerdebug/git/commits{/sha}", "comments_url": "https://api.github.com/repos/kgibm/dockerdebug/comments{/number}", "issue_comment_url": "https://api.github.com/repos/kgibm/dockerdebug/issues/comments{/number}", "contents_url": "https://api.github.com/repos/kgibm/dockerdebug/contents/{+path}", "compare_url": "https://api.github.com/repos/kgibm/dockerdebug/compare/{base}...{head}", "merges_url": "https://api.github.com/repos/kgibm/dockerdebug/merges", "archive_url": "https://api.github.com/repos/kgibm/dockerdebug/{archive_format}{/ref}", "downloads_url": "https://api.github.com/repos/kgibm/dockerdebug/downloads", "issues_url": "https://api.github.com/repos/kgibm/dockerdebug/issues{/number}", "pulls_url": "https://api.github.com/repos/kgibm/dockerdebug/pulls{/number}", "milestones_url": "https://api.github.com/repos/kgibm/dockerdebug/milestones{/number}", "notifications_url": "https://api.github.com/repos/kgibm/dockerdebug/notifications{?since,all,participating}", "labels_url": "https://api.github.com/repos/kgibm/dockerdebug/labels{/name}", "releases_url": "https://api.github.com/repos/kgibm/dockerdebug/releases{/id}", "deployments_url": "https://api.github.com/repos/kgibm/dockerdebug/deployments", "created_at": "2019-03-12T16:25:30Z", "updated_at": "2022-03-23T11:05:40Z", "pushed_at": "2022-08-16T17:32:47Z", "git_url": "git://github.com/kgibm/dockerdebug.git", "ssh_url": "git@github.com:kgibm/dockerdebug.git", "clone_url": "https://github.com/kgibm/dockerdebug.git", "svn_url": "https://github.com/kgibm/dockerdebug", "homepage": null, "size": 1243173, "stargazers_count": 33, "watchers_count": 33, "language": "Dockerfile", "has_issues": true, "has_projects": true, "has_downloads": true, "has_wiki": true, "has_pages": false, "forks_count": 18, "mirror_url": null, "archived": false, "disabled": false, "open_issues_count": 0, "license": {"key": "apache-2.0", "name": "Apache License 2.0", "spdx_id": "Apache-2.0", "url": "https://api.github.com/licenses/apache-2.0", "node_id": "MDc6TGljZW5zZTI="}, "allow_forking": true, "is_template": false, "web_commit_signoff_required": false, "topics": [], "visibility": "public", "forks": 18, "open_issues": 0, "watchers": 33, "default_branch": "master", "permissions": {"admin": false, "maintain": false, "push": false, "triage": false, "pull": true}}, {"id": 169291744, "node_id": "MDEwOlJlcG9zaXRvcnkxNjkyOTE3NDQ=", "name": "was_data_mining", "full_name": "kgibm/was_data_mining", "private": false, "owner": {"login": "kgibm", "id": 6618433, "node_id": "MDQ6VXNlcjY2MTg0MzM=", "avatar_url": "https://avatars.githubusercontent.com/u/6618433?v=4", "gravatar_id": "", "url": "https://api.github.com/users/kgibm", "html_url": "https://github.com/kgibm", "followers_url": "https://api.github.com/users/kgibm/followers", "following_url": "https://api.github.com/users/kgibm/following{/other_user}", "gists_url": "https://api.github.com/users/kgibm/gists{/gist_id}", "starred_url": "https://api.github.com/users/kgibm/starred{/owner}{/repo}", "subscriptions_url": "https://api.github.com/users/kgibm/subscriptions", "organizations_url": "https://api.github.com/users/kgibm/orgs", "repos_url": "https://api.github.com/users/kgibm/repos", "events_url": "https://api.github.com/users/kgibm/events{/privacy}", "received_events_url": "https://api.github.com/users/kgibm/received_events", "type": "User", "site_admin": false}, "html_url": "https://github.com/kgibm/was_data_mining", "description": null, "fork": false, "url": "https://api.github.com/repos/kgibm/was_data_mining", "forks_url": "https://api.github.com/repos/kgibm/was_data_mining/forks", "keys_url": "https://api.github.com/repos/kgibm/was_data_mining/keys{/key_id}", "collaborators_url": "https://api.github.com/repos/kgibm/was_data_mining/collaborators{/collaborator}", "teams_url": "https://api.github.com/repos/kgibm/was_data_mining/teams", "hooks_url": "https://api.github.com/repos/kgibm/was_data_mining/hooks", "issue_events_url": "https://api.github.com/repos/kgibm/was_data_mining/issues/events{/number}", "events_url": "https://api.github.com/repos/kgibm/was_data_mining/events", "assignees_url": "https://api.github.com/repos/kgibm/was_data_mining/assignees{/user}", "branches_url": "https://api.github.com/repos/kgibm/was_data_mining/branches{/branch}", "tags_url": "https://api.github.com/repos/kgibm/was_data_mining/tags", "blobs_url": "https://api.github.com/repos/kgibm/was_data_mining/git/blobs{/sha}", "git_tags_url": "https://api.github.com/repos/kgibm/was_data_mining/git/tags{/sha}", "git_refs_url": "https://api.github.com/repos/kgibm/was_data_mining/git/refs{/sha}", "trees_url": "https://api.github.com/repos/kgibm/was_data_mining/git/trees{/sha}", "statuses_url": "https://api.github.com/repos/kgibm/was_data_mining/statuses/{sha}", "languages_url": "https://api.github.com/repos/kgibm/was_data_mining/languages", "stargazers_url": "https://api.github.com/repos/kgibm/was_data_mining/stargazers", "contributors_url": "https://api.github.com/repos/kgibm/was_data_mining/contributors", "subscribers_url": "https://api.github.com/repos/kgibm/was_data_mining/subscribers", "subscription_url": "https://api.github.com/repos/kgibm/was_data_mining/subscription", "commits_url": "https://api.github.com/repos/kgibm/was_data_mining/commits{/sha}", "git_commits_url": "https://api.github.com/repos/kgibm/was_data_mining/git/commits{/sha}", "comments_url": "https://api.github.com/repos/kgibm/was_data_mining/comments{/number}", "issue_comment_url": "https://api.github.com/repos/kgibm/was_data_mining/issues/comments{/number}", "contents_url": "https://api.github.com/repos/kgibm/was_data_mining/contents/{+path}", "compare_url": "https://api.github.com/repos/kgibm/was_data_mining/compare/{base}...{head}", "merges_url": "https://api.github.com/repos/kgibm/was_data_mining/merges", "archive_url": "https://api.github.com/repos/kgibm/was_data_mining/{archive_format}{/ref}", "downloads_url": "https://api.github.com/repos/kgibm/was_data_mining/downloads", "issues_url": "https://api.github.com/repos/kgibm/was_data_mining/issues{/number}", "pulls_url": "https://api.github.com/repos/kgibm/was_data_mining/pulls{/number}", "milestones_url": "https://api.github.com/repos/kgibm/was_data_mining/milestones{/number}", "notifications_url": "https://api.github.com/repos/kgibm/was_data_mining/notifications{?since,all,participating}", "labels_url": "https://api.github.com/repos/kgibm/was_data_mining/labels{/name}", "releases_url": "https://api.github.com/repos/kgibm/was_data_mining/releases{/id}", "deployments_url": "https://api.github.com/repos/kgibm/was_data_mining/deployments", "created_at": "2019-02-05T18:36:57Z", "updated_at": "2020-05-25T06:42:55Z", "pushed_at": "2020-02-10T18:17:00Z", "git_url": "git://github.com/kgibm/was_data_mining.git", "ssh_url": "git@github.com:kgibm/was_data_mining.git", "clone_url": "https://github.com/kgibm/was_data_mining.git", "svn_url": "https://github.com/kgibm/was_data_mining", "homepage": null, "size": 235, "stargazers_count": 4, "watchers_count": 4, "language": "Python", "has_issues": true, "has_projects": true, "has_downloads": true, "has_wiki": true, "has_pages": false, "forks_count": 0, "mirror_url": null, "archived": false, "disabled": false, "open_issues_count": 2, "license": {"key": "epl-2.0", "name": "Eclipse Public License 2.0", "spdx_id": "EPL-2.0", "url": "https://api.github.com/licenses/epl-2.0", "node_id": "MDc6TGljZW5zZTMy"}, "allow_forking": true, "is_template": false, "web_commit_signoff_required": false, "topics": [], "visibility": "public", "forks": 0, "open_issues": 2, "watchers": 4, "default_branch": "master", "permissions": {"admin": false, "maintain": false, "push": false, "triage": false, "pull": true}}, {"id": 146916198, "node_id": "MDEwOlJlcG9zaXRvcnkxNDY5MTYxOTg=", "name": "una-tapa.github.io", "full_name": "una-tapa/una-tapa.github.io", "private": false, "owner": {"login": "una-tapa", "id": 20607354, "node_id": "MDQ6VXNlcjIwNjA3MzU0", "avatar_url": "https://avatars.githubusercontent.com/u/20607354?v=4", "gravatar_id": "", "url": "https://api.github.com/users/una-tapa", "html_url": "https://github.com/una-tapa", "followers_url": "https://api.github.com/users/una-tapa/followers", "following_url": "https://api.github.com/users/una-tapa/following{/other_user}", "gists_url": "https://api.github.com/users/una-tapa/gists{/gist_id}", "starred_url": "https://api.github.com/users/una-tapa/starred{/owner}{/repo}", "subscriptions_url": "https://api.github.com/users/una-tapa/subscriptions", "organizations_url": "https://api.github.com/users/una-tapa/orgs", "repos_url": "https://api.github.com/users/una-tapa/repos", "events_url": "https://api.github.com/users/una-tapa/events{/privacy}", "received_events_url": "https://api.github.com/users/una-tapa/received_events", "type": "User", "site_admin": false}, "html_url": "https://github.com/una-tapa/una-tapa.github.io", "description": null, "fork": false, "url": "https://api.github.com/repos/una-tapa/una-tapa.github.io", "forks_url": "https://api.github.com/repos/una-tapa/una-tapa.github.io/forks", "keys_url": "https://api.github.com/repos/una-tapa/una-tapa.github.io/keys{/key_id}", "collaborators_url": "https://api.github.com/repos/una-tapa/una-tapa.github.io/collaborators{/collaborator}", "teams_url": "https://api.github.com/repos/una-tapa/una-tapa.github.io/teams", "hooks_url": "https://api.github.com/repos/una-tapa/una-tapa.github.io/hooks", "issue_events_url": "https://api.github.com/repos/una-tapa/una-tapa.github.io/issues/events{/number}", "events_url": "https://api.github.com/repos/una-tapa/una-tapa.github.io/events", "assignees_url": "https://api.github.com/repos/una-tapa/una-tapa.github.io/assignees{/user}", "branches_url": "https://api.github.com/repos/una-tapa/una-tapa.github.io/branches{/branch}", "tags_url": "https://api.github.com/repos/una-tapa/una-tapa.github.io/tags", "blobs_url": "https://api.github.com/repos/una-tapa/una-tapa.github.io/git/blobs{/sha}", "git_tags_url": "https://api.github.com/repos/una-tapa/una-tapa.github.io/git/tags{/sha}", "git_refs_url": "https://api.github.com/repos/una-tapa/una-tapa.github.io/git/refs{/sha}", "trees_url": "https://api.github.com/repos/una-tapa/una-tapa.github.io/git/trees{/sha}", "statuses_url": "https://api.github.com/repos/una-tapa/una-tapa.github.io/statuses/{sha}", "languages_url": "https://api.github.com/repos/una-tapa/una-tapa.github.io/languages", "stargazers_url": "https://api.github.com/repos/una-tapa/una-tapa.github.io/stargazers", "contributors_url": "https://api.github.com/repos/una-tapa/una-tapa.github.io/contributors", "subscribers_url": "https://api.github.com/repos/una-tapa/una-tapa.github.io/subscribers", "subscription_url": "https://api.github.com/repos/una-tapa/una-tapa.github.io/subscription", "commits_url": "https://api.github.com/repos/una-tapa/una-tapa.github.io/commits{/sha}", "git_commits_url": "https://api.github.com/repos/una-tapa/una-tapa.github.io/git/commits{/sha}", "comments_url": "https://api.github.com/repos/una-tapa/una-tapa.github.io/comments{/number}", "issue_comment_url": "https://api.github.com/repos/una-tapa/una-tapa.github.io/issues/comments{/number}", "contents_url": "https://api.github.com/repos/una-tapa/una-tapa.github.io/contents/{+path}", "compare_url": "https://api.github.com/repos/una-tapa/una-tapa.github.io/compare/{base}...{head}", "merges_url": "https://api.github.com/repos/una-tapa/una-tapa.github.io/merges", "archive_url": "https://api.github.com/repos/una-tapa/una-tapa.github.io/{archive_format}{/ref}", "downloads_url": "https://api.github.com/repos/una-tapa/una-tapa.github.io/downloads", "issues_url": "https://api.github.com/repos/una-tapa/una-tapa.github.io/issues{/number}", "pulls_url": "https://api.github.com/repos/una-tapa/una-tapa.github.io/pulls{/number}", "milestones_url": "https://api.github.com/repos/una-tapa/una-tapa.github.io/milestones{/number}", "notifications_url": "https://api.github.com/repos/una-tapa/una-tapa.github.io/notifications{?since,all,participating}", "labels_url": "https://api.github.com/repos/una-tapa/una-tapa.github.io/labels{/name}", "releases_url": "https://api.github.com/repos/una-tapa/una-tapa.github.io/releases{/id}", "deployments_url": "https://api.github.com/repos/una-tapa/una-tapa.github.io/deployments", "created_at": "2018-08-31T16:21:30Z", "updated_at": "2020-05-15T21:07:26Z", "pushed_at": "2020-05-15T21:07:23Z", "git_url": "git://github.com/una-tapa/una-tapa.github.io.git", "ssh_url": "git@github.com:una-tapa/una-tapa.github.io.git", "clone_url": "https://github.com/una-tapa/una-tapa.github.io.git", "svn_url": "https://github.com/una-tapa/una-tapa.github.io", "homepage": null, "size": 6, "stargazers_count": 1, "watchers_count": 1, "language": null, "has_issues": true, "has_projects": true, "has_downloads": true, "has_wiki": true, "has_pages": true, "forks_count": 0, "mirror_url": null, "archived": false, "disabled": false, "open_issues_count": 0, "license": null, "allow_forking": true, "is_template": false, "web_commit_signoff_required": false, "topics": [], "visibility": "public", "forks": 0, "open_issues": 0, "watchers": 1, "default_branch": "master", "permissions": {"admin": false, "maintain": false, "push": false, "triage": false, "pull": true}}, {"id": 48957407, "node_id": "MDEwOlJlcG9zaXRvcnk0ODk1NzQwNw==", "name": "simulating", "full_name": "ncase/simulating", "private": false, "owner": {"login": "ncase", "id": 825858, "node_id": "MDQ6VXNlcjgyNTg1OA==", "avatar_url": "https://avatars.githubusercontent.com/u/825858?v=4", "gravatar_id": "", "url": "https://api.github.com/users/ncase", "html_url": "https://github.com/ncase", "followers_url": "https://api.github.com/users/ncase/followers", "following_url": "https://api.github.com/users/ncase/following{/other_user}", "gists_url": "https://api.github.com/users/ncase/gists{/gist_id}", "starred_url": "https://api.github.com/users/ncase/starred{/owner}{/repo}", "subscriptions_url": "https://api.github.com/users/ncase/subscriptions", "organizations_url": "https://api.github.com/users/ncase/orgs", "repos_url": "https://api.github.com/users/ncase/repos", "events_url": "https://api.github.com/users/ncase/events{/privacy}", "received_events_url": "https://api.github.com/users/ncase/received_events", "type": "User", "site_admin": false}, "html_url": "https://github.com/ncase/simulating", "description": "An interactive guide to thinking in systems!", "fork": false, "url": "https://api.github.com/repos/ncase/simulating", "forks_url": "https://api.github.com/repos/ncase/simulating/forks", "keys_url": "https://api.github.com/repos/ncase/simulating/keys{/key_id}", "collaborators_url": "https://api.github.com/repos/ncase/simulating/collaborators{/collaborator}", "teams_url": "https://api.github.com/repos/ncase/simulating/teams", "hooks_url": "https://api.github.com/repos/ncase/simulating/hooks", "issue_events_url": "https://api.github.com/repos/ncase/simulating/issues/events{/number}", "events_url": "https://api.github.com/repos/ncase/simulating/events", "assignees_url": "https://api.github.com/repos/ncase/simulating/assignees{/user}", "branches_url": "https://api.github.com/repos/ncase/simulating/branches{/branch}", "tags_url": "https://api.github.com/repos/ncase/simulating/tags", "blobs_url": "https://api.github.com/repos/ncase/simulating/git/blobs{/sha}", "git_tags_url": "https://api.github.com/repos/ncase/simulating/git/tags{/sha}", "git_refs_url": "https://api.github.com/repos/ncase/simulating/git/refs{/sha}", "trees_url": "https://api.github.com/repos/ncase/simulating/git/trees{/sha}", "statuses_url": "https://api.github.com/repos/ncase/simulating/statuses/{sha}", "languages_url": "https://api.github.com/repos/ncase/simulating/languages", "stargazers_url": "https://api.github.com/repos/ncase/simulating/stargazers", "contributors_url": "https://api.github.com/repos/ncase/simulating/contributors", "subscribers_url": "https://api.github.com/repos/ncase/simulating/subscribers", "subscription_url": "https://api.github.com/repos/ncase/simulating/subscription", "commits_url": "https://api.github.com/repos/ncase/simulating/commits{/sha}", "git_commits_url": "https://api.github.com/repos/ncase/simulating/git/commits{/sha}", "comments_url": "https://api.github.com/repos/ncase/simulating/comments{/number}", "issue_comment_url": "https://api.github.com/repos/ncase/simulating/issues/comments{/number}", "contents_url": "https://api.github.com/repos/ncase/simulating/contents/{+path}", "compare_url": "https://api.github.com/repos/ncase/simulating/compare/{base}...{head}", "merges_url": "https://api.github.com/repos/ncase/simulating/merges", "archive_url": "https://api.github.com/repos/ncase/simulating/{archive_format}{/ref}", "downloads_url": "https://api.github.com/repos/ncase/simulating/downloads", "issues_url": "https://api.github.com/repos/ncase/simulating/issues{/number}", "pulls_url": "https://api.github.com/repos/ncase/simulating/pulls{/number}", "milestones_url": "https://api.github.com/repos/ncase/simulating/milestones{/number}", "notifications_url": "https://api.github.com/repos/ncase/simulating/notifications{?since,all,participating}", "labels_url": "https://api.github.com/repos/ncase/simulating/labels{/name}", "releases_url": "https://api.github.com/repos/ncase/simulating/releases{/id}", "deployments_url": "https://api.github.com/repos/ncase/simulating/deployments", "created_at": "2016-01-03T19:08:55Z", "updated_at": "2022-10-11T19:21:32Z", "pushed_at": "2020-01-06T21:16:57Z", "git_url": "git://github.com/ncase/simulating.git", "ssh_url": "git@github.com:ncase/simulating.git", "clone_url": "https://github.com/ncase/simulating.git", "svn_url": "https://github.com/ncase/simulating", "homepage": "http://ncase.me/simulating", "size": 2391, "stargazers_count": 179, "watchers_count": 179, "language": "JavaScript", "has_issues": true, "has_projects": true, "has_downloads": true, "has_wiki": true, "has_pages": true, "forks_count": 21, "mirror_url": null, "archived": false, "disabled": false, "open_issues_count": 7, "license": null, "allow_forking": true, "is_template": false, "web_commit_signoff_required": false, "topics": [], "visibility": "public", "forks": 21, "open_issues": 7, "watchers": 179, "default_branch": "gh-pages", "permissions": {"admin": false, "maintain": false, "push": false, "triage": false, "pull": true}}, {"id": 21836148, "node_id": "MDEwOlJlcG9zaXRvcnkyMTgzNjE0OA==", "name": "OptiKey", "full_name": "OptiKey/OptiKey", "private": false, "owner": {"login": "OptiKey", "id": 15629872, "node_id": "MDEyOk9yZ2FuaXphdGlvbjE1NjI5ODcy", "avatar_url": "https://avatars.githubusercontent.com/u/15629872?v=4", "gravatar_id": "", "url": "https://api.github.com/users/OptiKey", "html_url": "https://github.com/OptiKey", "followers_url": "https://api.github.com/users/OptiKey/followers", "following_url": "https://api.github.com/users/OptiKey/following{/other_user}", "gists_url": "https://api.github.com/users/OptiKey/gists{/gist_id}", "starred_url": "https://api.github.com/users/OptiKey/starred{/owner}{/repo}", "subscriptions_url": "https://api.github.com/users/OptiKey/subscriptions", "organizations_url": "https://api.github.com/users/OptiKey/orgs", "repos_url": "https://api.github.com/users/OptiKey/repos", "events_url": "https://api.github.com/users/OptiKey/events{/privacy}", "received_events_url": "https://api.github.com/users/OptiKey/received_events", "type": "Organization", "site_admin": false}, "html_url": "https://github.com/OptiKey/OptiKey", "description": "OptiKey - Full computer control and speech with your eyes", "fork": false, "url": "https://api.github.com/repos/OptiKey/OptiKey", "forks_url": "https://api.github.com/repos/OptiKey/OptiKey/forks", "keys_url": "https://api.github.com/repos/OptiKey/OptiKey/keys{/key_id}", "collaborators_url": "https://api.github.com/repos/OptiKey/OptiKey/collaborators{/collaborator}", "teams_url": "https://api.github.com/repos/OptiKey/OptiKey/teams", "hooks_url": "https://api.github.com/repos/OptiKey/OptiKey/hooks", "issue_events_url": "https://api.github.com/repos/OptiKey/OptiKey/issues/events{/number}", "events_url": "https://api.github.com/repos/OptiKey/OptiKey/events", "assignees_url": "https://api.github.com/repos/OptiKey/OptiKey/assignees{/user}", "branches_url": "https://api.github.com/repos/OptiKey/OptiKey/branches{/branch}", "tags_url": "https://api.github.com/repos/OptiKey/OptiKey/tags", "blobs_url": "https://api.github.com/repos/OptiKey/OptiKey/git/blobs{/sha}", "git_tags_url": "https://api.github.com/repos/OptiKey/OptiKey/git/tags{/sha}", "git_refs_url": "https://api.github.com/repos/OptiKey/OptiKey/git/refs{/sha}", "trees_url": "https://api.github.com/repos/OptiKey/OptiKey/git/trees{/sha}", "statuses_url": "https://api.github.com/repos/OptiKey/OptiKey/statuses/{sha}", "languages_url": "https://api.github.com/repos/OptiKey/OptiKey/languages", "stargazers_url": "https://api.github.com/repos/OptiKey/OptiKey/stargazers", "contributors_url": "https://api.github.com/repos/OptiKey/OptiKey/contributors", "subscribers_url": "https://api.github.com/repos/OptiKey/OptiKey/subscribers", "subscription_url": "https://api.github.com/repos/OptiKey/OptiKey/subscription", "commits_url": "https://api.github.com/repos/OptiKey/OptiKey/commits{/sha}", "git_commits_url": "https://api.github.com/repos/OptiKey/OptiKey/git/commits{/sha}", "comments_url": "https://api.github.com/repos/OptiKey/OptiKey/comments{/number}", "issue_comment_url": "https://api.github.com/repos/OptiKey/OptiKey/issues/comments{/number}", "contents_url": "https://api.github.com/repos/OptiKey/OptiKey/contents/{+path}", "compare_url": "https://api.github.com/repos/OptiKey/OptiKey/compare/{base}...{head}", "merges_url": "https://api.github.com/repos/OptiKey/OptiKey/merges", "archive_url": "https://api.github.com/repos/OptiKey/OptiKey/{archive_format}{/ref}", "downloads_url": "https://api.github.com/repos/OptiKey/OptiKey/downloads", "issues_url": "https://api.github.com/repos/OptiKey/OptiKey/issues{/number}", "pulls_url": "https://api.github.com/repos/OptiKey/OptiKey/pulls{/number}", "milestones_url": "https://api.github.com/repos/OptiKey/OptiKey/milestones{/number}", "notifications_url": "https://api.github.com/repos/OptiKey/OptiKey/notifications{?since,all,participating}", "labels_url": "https://api.github.com/repos/OptiKey/OptiKey/labels{/name}", "releases_url": "https://api.github.com/repos/OptiKey/OptiKey/releases{/id}", "deployments_url": "https://api.github.com/repos/OptiKey/OptiKey/deployments", "created_at": "2014-07-14T21:23:52Z", "updated_at": "2022-10-24T23:43:06Z", "pushed_at": "2022-10-22T20:55:36Z", "git_url": "git://github.com/OptiKey/OptiKey.git", "ssh_url": "git@github.com:OptiKey/OptiKey.git", "clone_url": "https://github.com/OptiKey/OptiKey.git", "svn_url": "https://github.com/OptiKey/OptiKey", "homepage": "http://www.optikey.org", "size": 365860, "stargazers_count": 3971, "watchers_count": 3971, "language": "C#", "has_issues": true, "has_projects": true, "has_downloads": true, "has_wiki": true, "has_pages": true, "forks_count": 504, "mirror_url": null, "archived": false, "disabled": false, "open_issues_count": 87, "license": {"key": "gpl-3.0", "name": "GNU General Public License v3.0", "spdx_id": "GPL-3.0", "url": "https://api.github.com/licenses/gpl-3.0", "node_id": "MDc6TGljZW5zZTk="}, "allow_forking": true, "is_template": false, "web_commit_signoff_required": false, "topics": ["aac", "accessibility", "accessible", "als", "assistive-technology", "c-sharp", "communication", "disabilities", "disabilty", "eye-tracker", "eye-tracking", "eyes", "eyetracking", "mnd", "optikey", "screen-keyboard"], "visibility": "public", "forks": 504, "open_issues": 87, "watchers": 3971, "default_branch": "master", "permissions": {"admin": false, "maintain": false, "push": false, "triage": false, "pull": true}}]