{"login": "jefftrudeau", "id": 488977, "node_id": "MDQ6VXNlcjQ4ODk3Nw==", "avatar_url": "https://avatars.githubusercontent.com/u/488977?v=4", "gravatar_id": "", "url": "https://api.github.com/users/jefftrudeau", "html_url": "https://github.com/jefftrudeau", "followers_url": "https://api.github.com/users/jefftrudeau/followers", "following_url": "https://api.github.com/users/jefftrudeau/following{/other_user}", "gists_url": "https://api.github.com/users/jefftrudeau/gists{/gist_id}", "starred_url": "https://api.github.com/users/jefftrudeau/starred{/owner}{/repo}", "subscriptions_url": "https://api.github.com/users/jefftrudeau/subscriptions", "organizations_url": "https://api.github.com/users/jefftrudeau/orgs", "repos_url": "https://api.github.com/users/jefftrudeau/repos", "events_url": "https://api.github.com/users/jefftrudeau/events{/privacy}", "received_events_url": "https://api.github.com/users/jefftrudeau/received_events", "type": "User", "site_admin": false, "name": "Jeff Trudeau", "company": null, "blog": "https://www.braeburn.tech", "location": "Boston, MA", "email": null, "hireable": true, "bio": "Co-Founder @InspiredMember;\r\nFounder, Principal @braeburntech", "twitter_username": null, "public_repos": 9, "public_gists": 2, "followers": 8, "following": 13, "created_at": "2010-11-19T20:47:03Z", "updated_at": "2022-08-30T16:20:53Z"}