{"login": "vladanghene", "id": 3773948, "node_id": "MDQ6VXNlcjM3NzM5NDg=", "avatar_url": "https://avatars.githubusercontent.com/u/3773948?v=4", "gravatar_id": "", "url": "https://api.github.com/users/vladanghene", "html_url": "https://github.com/vladanghene", "followers_url": "https://api.github.com/users/vladanghene/followers", "following_url": "https://api.github.com/users/vladanghene/following{/other_user}", "gists_url": "https://api.github.com/users/vladanghene/gists{/gist_id}", "starred_url": "https://api.github.com/users/vladanghene/starred{/owner}{/repo}", "subscriptions_url": "https://api.github.com/users/vladanghene/subscriptions", "organizations_url": "https://api.github.com/users/vladanghene/orgs", "repos_url": "https://api.github.com/users/vladanghene/repos", "events_url": "https://api.github.com/users/vladanghene/events{/privacy}", "received_events_url": "https://api.github.com/users/vladanghene/received_events", "type": "User", "site_admin": false, "name": "AVA", "company": "dev-/", "blog": "http://memory-alpha.wikia.com/wiki/Vulcan_High_Council", "location": "Vulcan", "email": null, "hireable": true, "bio": "Veni - vidi - codi\r\nDiscord: cycle337#3531", "twitter_username": null, "public_repos": 71, "public_gists": 15, "followers": 33, "following": 307, "created_at": "2013-03-05T08:27:44Z", "updated_at": "2022-05-02T14:23:26Z"}