{"login": "ssdavenport", "id": 814918, "node_id": "MDQ6VXNlcjgxNDkxOA==", "avatar_url": "https://avatars.githubusercontent.com/u/814918?v=4", "gravatar_id": "", "url": "https://api.github.com/users/ssdavenport", "html_url": "https://github.com/ssdavenport", "followers_url": "https://api.github.com/users/ssdavenport/followers", "following_url": "https://api.github.com/users/ssdavenport/following{/other_user}", "gists_url": "https://api.github.com/users/ssdavenport/gists{/gist_id}", "starred_url": "https://api.github.com/users/ssdavenport/starred{/owner}{/repo}", "subscriptions_url": "https://api.github.com/users/ssdavenport/subscriptions", "organizations_url": "https://api.github.com/users/ssdavenport/orgs", "repos_url": "https://api.github.com/users/ssdavenport/repos", "events_url": "https://api.github.com/users/ssdavenport/events{/privacy}", "received_events_url": "https://api.github.com/users/ssdavenport/received_events", "type": "User", "site_admin": false, "name": "Steven Davenport", "company": null, "blog": "", "location": "Los Angeles, CA", "email": null, "hireable": true, "bio": "I do research, often about cannabis.\r\nPh.D. Candidate, Policy Analysis, RAND Graduate School.\r\nM.S. Public Policy (Data Analytics), Carnegie Mellon University", "twitter_username": null, "public_repos": 14, "public_gists": 0, "followers": 9, "following": 3, "created_at": "2011-05-27T19:49:08Z", "updated_at": "2021-05-28T17:35:04Z"}